README.txt
setup.py
GaeAssetBundler.egg-info/PKG-INFO
GaeAssetBundler.egg-info/SOURCES.txt
GaeAssetBundler.egg-info/dependency_links.txt
GaeAssetBundler.egg-info/requires.txt
GaeAssetBundler.egg-info/top_level.txt
gae_asset_bundler/__init__.py
gae_asset_bundler/gae_asset_bundler.py
scripts/__init__.py