Metadata-Version: 1.0
Name: GaeAssetBundler
Version: 0.3
Summary: Assets compression and bundling for GAE
Home-page: UNKNOWN
Author: Fabio Sussetto
Author-email: fabio@bynd.com
License: UNKNOWN
Platform: UNKNOWN
